{
  "title": "Comprehensive Guide to Major Cities in the South of France",
  "outline": [
    {
      "level": "H1",
      "text": "Comprehensive Guide to Major Cities in the South of France",
      "page": 0
    },
    {
      "level": "H2",
      "text": "Introduction",
      "page": 0
    },
    {
      "level": "H2",
      "text": "Overview of the Region",
      "page": 1
    },
    {
      "level": "H2",
      "text": "Marseille: The Oldest City in France",
      "page": 2
    },
    {
      "level": "H2",
      "text": "Nice: The Jewel of the French Riviera",
      "page": 4
    },
    {
      "level": "H2",
      "text": "Avignon: The City of Popes",
      "page": 6
    },
    {
      "level": "H2",
      "text": "Aix-en-Provence: A City of Art and Culture",
      "page": 7
    },
    {
      "level": "H2",
      "text": "Toulouse: The Pink City",
      "page": 8
    },
    {
      "level": "H1",
      "text": "Montpellier: A University City with Medieval Charm",
      "page": 9
    },
    {
      "level": "H2",
      "text": "Perpignan: A Blend of French and Catalan Cultures",
      "page": 10
    },
    {
      "level": "H2",
      "text": "Arles: A Roman Treasure",
      "page": 11
    },
    {
      "level": "H2",
      "text": "Carcassonne: A Medieval Fortress",
      "page": 12
    },
    {
      "level": "H2",
      "text": "Conclusion",
      "page": 13
    }
  ]
}